src/modules/data_path/ram.v
module ram(output reg[31:0] data_out,
           output reg moc,
           input enable,
           read_write,
           sig,
           input [1:0] data_length,
           input[8:0] address,
           input[31:0] data_in);

parameter BYTE       = 2'd0;
parameter HALFWORD   = 2'd1;
parameter WORD       = 2'd2;
parameter DOUBLEWORD = 2'd3;
integer temp;

reg [7:0] memory[0:511];
always @(enable, read_write, address, data_in, data_length)
    if (enable)
    begin
        moc <= 1'b0;
        case(data_length)
            BYTE:
            begin
                if (read_write)
                begin
                    data_out = 0;
                    data_out = memory[address];
                end
                
                else
                begin
                    memory[address] = data_in[7:0];
                end
            end
            HALFWORD:
            begin
                if (read_write)
                begin
                    data_out       = 0;
                    data_out[15:8] = memory[address];
                    data_out[7:0]  = memory[address + 1];
                end
                
                else
                begin
                    memory[address]     = data_in[15:8];
                    memory[address + 1] = data_in[7:0];
                end
            end
            WORD:
            begin
                if (read_write)
                begin
                    data_out[31:24] = memory[address];
                    data_out[23:16] = memory[address + 1];
                    data_out[15:8]  = memory[address + 2];
                    data_out[7:0]   = memory[address + 3];
                end
                
                else
                begin
                    memory[address]     = data_in[31:24];
                    memory[address + 1] = data_in[23:16];
                    memory[address + 2] = data_in[15:8];
                    memory[address + 3] = data_in[7:0];
                end
            end
            DOUBLEWORD:
            begin
                if (read_write)
                begin
                    temp = address;
                    repeat(2)
                    begin
                        data_out[31:24] = memory[temp];
                        data_out[23:16] = memory[temp + 1];
                        data_out[15:8]  = memory[temp + 2];
                        data_out[7:0]   = memory[temp + 3];
                        temp            = temp + 4;
                    end
                end
                
                else
                begin
                    temp = address;
                    repeat(2)
                    begin
                        memory[temp]     = data_in[31:24];
                        memory[temp + 1] = data_in[23:16];
                        memory[temp + 2] = data_in[15:8];
                        memory[temp + 3] = data_in[7:0];
                        temp             = temp + 4;
                    end
                end
            end
        endcase
        
        moc <= 1'b1;
    end

else
moc <= 1'b0;

endmodule

src/tests/ram_test.v
`include "src/modules/data_path/ram.v"
module ram_test();
    
    // Outputs
    wire [31:0] data_out;
    wire mfc;
    
    // Inputs
    reg enable, read_write, sig;
    reg [1:0] data_length;
    reg[8:0] address;
    reg [31:0] data_in;
    
    // Modules
    ram ram1(data_out, mfc, enable, read_write, sig, data_length, address, data_in);
    
    // Other
    integer fi, fo, i;
    reg [7:0]data;
    
    initial #500 $finish;
    
    // Precharge memory
    initial
    begin
        fi         = $fopen("res/ram_input_files/ram_input_1.txt", "r");
        address    = 9'd0;
        read_write = 1'b0;
        enable     = 1'b0;
        sig = 0;
        while(!$feof(fi))
        begin
            i                    = $fscanf(fi, "%d", data);
            ram1.memory[address] = data;
            address              = address + 1;
        end
        $fclose(fi);
    end
    
    // Read precharged memory
    initial
        #5 begin
        fo          = $fopen("res/ram_output_files/mem_content.txt");
        address     = 9'd0;
        read_write  = 1'b1;
        data_length = 2'b0;
        repeat(16)
        begin
            enable     = 1'b1;
            #5 enable  = 1'b0;
            #5 address = address + 1;
        end
    end
    
    // Write
    initial
        #170 begin
        read_write = 1'b0;
    
    // Write a byte to loc 0
    begin
    data_length = 2'd0;
    address     = 9'd0;
    data_in     = 32'h000000FF;
    sig = 1;
    enable      = 1'b1;
    #5 enable   = 1'b0;
    end
    // Write halfword to loc 2
    #10 begin
    data_length = 2'd1;
    address     = 9'd2;
    data_in     = 32'h0000FFFF;
    enable      = 1'b1;
    #5 enable   = 1'b0;
    end
    
    // Write halfword to loc 4
    #20 begin
    data_length = 2'd1;
    address     = 9'd4;
    data_in     = 32'h00000800;
    enable      = 1'b1;
    #5 enable   = 1'b0;
    end
    
    // Write word to loc 8
    #30 begin
    data_length = 2'd2;
    address     = 9'd8;
    data_in     = 32'h00100000;
    enable      = 1'b1;
    #5 enable   = 1'b0;
    end
    end
    
    // Read
    initial
        #255 begin
        read_write = 1'b1;
        data_in    = 0;
    
    // Read a byte from loc 0
    begin
    data_length = 2'd0;
    address     = 9'd0;
    enable      = 1'b1;
    #5 enable   = 1'b0;
    end
    // Read a halfword from loc 2
    #10 begin
    data_length = 2'd1;
    address     = 9'd2;
    enable      = 1'b1;
    #5 enable   = 1'b0;
    end
    
    // Read a halfword from loc 4
    #20 begin
    data_length = 2'd1;
    address     = 9'd4;
    enable      = 1'b1;
    #5 enable   = 1'b0;
    end
    
    // Read a word form loc 8
    #30 begin
    data_length = 2'd2;
    address     = 9'd8;
    enable      = 1'b1;
    #5 enable   = 1'b0;
    end
    end
    
    // Monitoring
    initial begin
        $dumpfile("bin/dumpfiles/ram_test.vcd");
        $dumpvars(0, ram_test);
        
        $display("\n*** RAM TEST ***");
        $display ("\ndata_out data_in  enable read_write data_length address mfc \t\t   time");
        $monitor("%b %h   %b \t     %b \t\t %b \t  %h\t %b %b %d", data_out, data_in, enable, read_write, data_length, address, mfc, sig, $time);
    end
    
    always @(negedge enable)
    begin
        $fdisplay(fo, "data out %d = %d  %d", address, data_out, $time);
    end
    
endmodule

bin/dumpfiles/ram_test.vcd
$date
	Fri May  8 14:33:12 2020
$end
$version
	Icarus Verilog
$end
$timescale
	1s
$end
$scope module ram_test $end
$var wire 1 ! mfc $end
$var wire 32 " data_out [31:0] $end
$var reg 9 # address [8:0] $end
$var reg 8 $ data [7:0] $end
$var reg 32 % data_in [31:0] $end
$var reg 2 & data_length [1:0] $end
$var reg 1 ' enable $end
$var reg 1 ( read_write $end
$var reg 1 ) sig $end
$var integer 32 * fi [31:0] $end
$var integer 32 + fo [31:0] $end
$var integer 32 , i [31:0] $end
$scope module ram1 $end
$var wire 9 - address [8:0] $end
$var wire 32 . data_in [31:0] $end
$var wire 2 / data_length [1:0] $end
$var wire 1 ' enable $end
$var wire 1 ( read_write $end
$var wire 1 ) sig $end
$var reg 32 0 data_out [31:0] $end
$var reg 1 ! moc $end
$var integer 32 1 temp [31:0] $end
$upscope $end
$upscope $end
$enddefinitions $end
#0
$dumpvars
bx 1
bx 0
bx /
bx .
b10000 -
b1 ,
bx +
b10000000000000000000000000000011 *
0)
0(
0'
bx &
bx %
b1111 $
b10000 #
bx "
0!
$end
#5
1!
b0 "
b0 0
1'
b0 &
b0 /
1(
b0 #
b0 -
b10 +
#10
0!
0'
#15
1!
b1 "
b1 0
1'
b1 #
b1 -
#20
0!
0'
#25
1!
b10 "
b10 0
1'
b10 #
b10 -
#30
0!
0'
#35
1!
b11 "
b11 0
1'
b11 #
b11 -
#40
0!
0'
#45
1!
b100 "
b100 0
1'
b100 #
b100 -
#50
0!
0'
#55
1!
b101 "
b101 0
1'
b101 #
b101 -
#60
0!
0'
#65
1!
b110 "
b110 0
1'
b110 #
b110 -
#70
0!
0'
#75
1!
b111 "
b111 0
1'
b111 #
b111 -
#80
0!
0'
#85
1!
b1000 "
b1000 0
1'
b1000 #
b1000 -
#90
0!
0'
#95
1!
b1001 "
b1001 0
1'
b1001 #
b1001 -
#100
0!
0'
#105
1!
b1010 "
b1010 0
1'
b1010 #
b1010 -
#110
0!
0'
#115
1!
b1011 "
b1011 0
1'
b1011 #
b1011 -
#120
0!
0'
#125
1!
b1100 "
b1100 0
1'
b1100 #
b1100 -
#130
0!
0'
#135
1!
b1101 "
b1101 0
1'
b1101 #
b1101 -
#140
0!
0'
#145
1!
b1110 "
b1110 0
1'
b1110 #
b1110 -
#150
0!
0'
#155
1!
b1111 "
b1111 0
1'
b1111 #
b1111 -
#160
0!
0'
#165
b10000 #
b10000 -
#170
1!
1'
1)
b11111111 %
b11111111 .
b0 #
b0 -
0(
#175
0!
0'
#185
1!
1'
b1111111111111111 %
b1111111111111111 .
b10 #
b10 -
b1 &
b1 /
#190
0!
0'
#210
1!
1'
b100000000000 %
b100000000000 .
b100 #
b100 -
#215
0!
0'
#245
1!
1'
b100000000000000000000 %
b100000000000000000000 .
b1000 #
b1000 -
b10 &
b10 /
#250
0!
0'
#255
1!
b11111111111111111111111111111111 "
b11111111111111111111111111111111 0
1'
b0 #
b0 -
b0 &
b0 /
b0 %
b0 .
1(
#260
0!
0'
#270
1!
b11111111111111111111111111111111 "
b11111111111111111111111111111111 0
1'
b10 #
b10 -
b1 &
b1 /
#275
0!
0'
#295
1!
b100000000000 "
b100000000000 0
1'
b100 #
b100 -
#300
0!
0'
#330
1!
b100000000000000000000 "
b100000000000000000000 0
1'
b1000 #
b1000 -
b10 &
b10 /
#335
0!
0'
