src/modules/ram.v
module ram(output reg[31:0] data_out,
           output reg mfc,
           input enable,
           read_write,
           input [1:0] data_length,
           input[8:0] address,
           input[31:0] data_in);

parameter BYTE       = 2'd0;
parameter HALFWORD   = 2'd1;
parameter WORD       = 2'd2;
parameter DOUBLEWORD = 2'd3;
integer temp;

reg [7:0] memory[0:511];
always @(enable, read_write)
    if (enable)
    begin
        mfc <= 1'b0;
        case(data_length)
            BYTE:
            begin #5
                if (read_write)
                begin
                    data_out = 0;
                    data_out = memory[address];
                end
                
                else
                begin
                    memory[address] = data_in[7:0];
                end
            end
            HALFWORD:
            begin #5
                if (read_write)
                begin
                    data_out = 0;
                    data_out[15:8]  = memory[address];
                    data_out[7:0] = memory[address + 1];
                end
                
                else
                begin
                    memory[address]     = data_in[15:8];
                    memory[address + 1] = data_in[7:0];
                end
            end
            WORD:
            begin #5
                if (read_write)
                begin
                    data_out[31:24]   = memory[address];
                    data_out[23:16]  = memory[address + 1];
                    data_out[15:8] = memory[address + 2];
                    data_out[7:0] = memory[address + 3];
                end
                
                else
                begin
                    memory[address]     = data_in[31:24];
                    memory[address + 1] = data_in[23:16];
                    memory[address + 2] = data_in[15:8];
                    memory[address + 3] = data_in[7:0];
                end
            end
            DOUBLEWORD:
            begin
                if (read_write)
                begin
                    temp = address;
                    repeat(2) #5
                    begin
                    data_out[31:24]   = memory[temp];
                    data_out[23:16]  = memory[temp + 1];
                    data_out[15:8] = memory[temp + 2];
                    data_out[7:0] = memory[temp + 3];
                    temp            = temp + 4;
                end
            end
            
            else
            begin
                temp = address;
                repeat(2) #5
                begin
                    memory[temp]     = data_in[31:24];
                    memory[temp + 1] = data_in[23:16];
                    memory[temp + 2] = data_in[15:8];
                    memory[temp + 3] = data_in[7:0];
                    temp             = temp + 4;
                end
            end
        end
        endcase

        mfc <= 1'b1;
    end

    else 
        mfc <= 1'b0;
    
endmodule

src/tests/ram_test.v
`include "src/modules/ram.v"
module ram_test();
    
    // Outputs
    wire [31:0] data_out;
    wire mfc;
    
    // Inputs
    reg enable, read_write;
    reg [1:0] data_length;
    reg[8:0] address;
    reg [31:0] data_in;
    
    // Modules
    ram ram1(data_out, mfc, enable, read_write, data_length, address, data_in);
    
    // Other
    integer fi, fo, i;
    reg [7:0]data;
    
    initial #500 $finish;
    
    // Precharge memory
    initial
    begin
        fi         = $fopen("res/ram_input_files/ram_input_1.txt", "r");
        address    = 9'd0;
        read_write = 1'b0;
        enable     = 1'b0;
        while(!$feof(fi))
        begin
            i                    = $fscanf(fi, "%d", data);
            ram1.memory[address] = data;
            address              = address + 1;
        end
        $fclose(fi);
    end
    
    // Read precharged memory
    initial
        #5 begin
        fo          = $fopen("res/ram_output_files/mem_content.txt");
        address     = 9'd0;
        read_write  = 1'b1;
        data_length = 2'b0;
        repeat(16)
        begin
            enable     = 1'b1;
            #5 enable  = 1'b0;
            #5 address = address + 1;
        end
    end
    
    // Write
    initial
        #170 begin
        read_write = 1'b0;
    
    // Write a byte to loc 0
    begin
    data_length = 2'd0;
    address     = 9'd0;
    data_in     = 32'h0000000A;
    enable      = 1'b1;
    #5 enable   = 1'b0;
    end
    // Write halfword to loc 2
    #10 begin
    data_length = 2'd1;
    address     = 9'd2;
    data_in     = 32'h00000400;
    enable      = 1'b1;
    #5 enable   = 1'b0;
    end
    
    // Write halfword to loc 4
    #20 begin
    data_length = 2'd1;
    address     = 9'd4;
    data_in     = 32'h00000800;
    enable      = 1'b1;
    #5 enable   = 1'b0;
    end
    
    // Write word to loc 8
    #30 begin
    data_length = 2'd2;
    address     = 9'd8;
    data_in     = 32'h00100000;
    enable      = 1'b1;
    #5 enable   = 1'b0;
    end
    end
    
    // Read
    initial
        #255 begin
        read_write = 1'b1;
        data_in    = 0;
    
    // Read a byte from loc 0
    begin
    data_length = 2'd0;
    address     = 9'd0;
    enable      = 1'b1;
    #5 enable   = 1'b0;
    end
    // Read a halfword from loc 2
    #10 begin
    data_length = 2'd1;
    address     = 9'd2;
    enable      = 1'b1;
    #5 enable   = 1'b0;
    end
    
    // Read a halfword from loc 4
    #20 begin
    data_length = 2'd1;
    address     = 9'd4;
    enable      = 1'b1;
    #5 enable   = 1'b0;
    end
    
    // Read a word form loc 8
    #30 begin
    data_length = 2'd2;
    address     = 9'd8;
    enable      = 1'b1;
    #5 enable   = 1'b0;
    end
    end
    
    // Monitoring
    initial begin
        $dumpfile("bin/dumpfiles/ram_test.vcd");
        $dumpvars(0, ram_test);
        
        $display("\n*** RAM TEST ***");
        $display ("\ndata_out data_in  enable read_write data_length address mfc \t\t   time");
        $monitor("%h %h   %b \t     %b \t\t %b \t  %h\t %b %d", data_out, data_in, enable, read_write, data_length, address, mfc, $time);
    end
    
    always @(negedge enable)
    begin
        $fdisplay(fo, "data out %d = %d  %d", address, data_out, $time);
    end
    
endmodule

bin/dumpfiles/ram_test.vcd
$date
	Mon Apr  6 19:42:56 2020
$end
$version
	Icarus Verilog
$end
$timescale
	1s
$end
$scope module ram_test $end
$var wire 1 ! mfc $end
$var wire 32 " data_out [31:0] $end
$var reg 9 # address [8:0] $end
$var reg 8 $ data [7:0] $end
$var reg 32 % data_in [31:0] $end
$var reg 2 & data_length [1:0] $end
$var reg 1 ' enable $end
$var reg 1 ( read_write $end
$var integer 32 ) fi [31:0] $end
$var integer 32 * fo [31:0] $end
$var integer 32 + i [31:0] $end
$scope module ram1 $end
$var wire 9 , address [8:0] $end
$var wire 32 - data_in [31:0] $end
$var wire 2 . data_length [1:0] $end
$var wire 1 ' enable $end
$var wire 1 ( read_write $end
$var reg 32 / data_out [31:0] $end
$var reg 1 ! mfc $end
$var integer 32 0 temp [31:0] $end
$upscope $end
$upscope $end
$enddefinitions $end
#0
$dumpvars
bx 0
bx /
bx .
bx -
b10000 ,
b1 +
bx *
b10000000000000000000000000000011 )
0(
0'
bx &
bx %
b1111 $
b10000 #
bx "
0!
$end
#5
1'
b0 &
b0 .
1(
b0 #
b0 ,
b10 *
#10
1!
b0 "
b0 /
0'
#15
0!
1'
b1 #
b1 ,
#20
1!
b1 "
b1 /
0'
#25
0!
1'
b10 #
b10 ,
#30
1!
b10 "
b10 /
0'
#35
0!
1'
b11 #
b11 ,
#40
1!
b11 "
b11 /
0'
#45
0!
1'
b100 #
b100 ,
#50
1!
b100 "
b100 /
0'
#55
0!
1'
b101 #
b101 ,
#60
1!
b101 "
b101 /
0'
#65
0!
1'
b110 #
b110 ,
#70
1!
b110 "
b110 /
0'
#75
0!
1'
b111 #
b111 ,
#80
1!
b111 "
b111 /
0'
#85
0!
1'
b1000 #
b1000 ,
#90
1!
b1000 "
b1000 /
0'
#95
0!
1'
b1001 #
b1001 ,
#100
1!
b1001 "
b1001 /
0'
#105
0!
1'
b1010 #
b1010 ,
#110
1!
b1010 "
b1010 /
0'
#115
0!
1'
b1011 #
b1011 ,
#120
1!
b1011 "
b1011 /
0'
#125
0!
1'
b1100 #
b1100 ,
#130
1!
b1100 "
b1100 /
0'
#135
0!
1'
b1101 #
b1101 ,
#140
1!
b1101 "
b1101 /
0'
#145
0!
1'
b1110 #
b1110 ,
#150
1!
b1110 "
b1110 /
0'
#155
0!
1'
b1111 #
b1111 ,
#160
1!
b1111 "
b1111 /
0'
#165
b10000 #
b10000 ,
#170
0!
1'
b1010 %
b1010 -
b0 #
b0 ,
0(
#175
1!
0'
#185
0!
1'
b10000000000 %
b10000000000 -
b10 #
b10 ,
b1 &
b1 .
#190
1!
0'
#210
0!
1'
b100000000000 %
b100000000000 -
b100 #
b100 ,
#215
1!
0'
#245
0!
1'
b100000000000000000000 %
b100000000000000000000 -
b1000 #
b1000 ,
b10 &
b10 .
#250
1!
0'
#255
0!
1'
b0 #
b0 ,
b0 &
b0 .
b0 %
b0 -
1(
#260
1!
b1010 "
b1010 /
0'
#270
0!
1'
b10 #
b10 ,
b1 &
b1 .
#275
1!
b10000000000 "
b10000000000 /
0'
#295
0!
1'
b100 #
b100 ,
#300
1!
b100000000000 "
b100000000000 /
0'
#330
0!
1'
b1000 #
b1000 ,
b10 &
b10 .
#335
1!
b100000000000000000000 "
b100000000000000000000 /
0'
